example/server/__init__.py
example/server/models.py
example/server/settings.py
example/server/urls.py
example/server/wsgi.py
example/server/tests/__init__.py
example/server/tests/test_model_changes.py
simple_diff/__init__.py
simple_diff/models.py
django_simple_diff-0.0.3.dist-info/LICENSE
django_simple_diff-0.0.3.dist-info/METADATA
django_simple_diff-0.0.3.dist-info/WHEEL
django_simple_diff-0.0.3.dist-info/top_level.txt
django_simple_diff-0.0.3.dist-info/RECORD
